django_cloudtasks/__init__.py
django_cloudtasks/admin.py
django_cloudtasks/apps.py
django_cloudtasks/constants.py
django_cloudtasks/decorators.py
django_cloudtasks/manager.py
django_cloudtasks/models.py
django_cloudtasks/tests.py
django_cloudtasks/urls.py
django_cloudtasks/utils.py
django_cloudtasks/views.py
django_cloudtasks/migrations/0001_initial.py
django_cloudtasks/migrations/__init__.py
django_gcp_cloudtasks-1.9.0.dist-info/licenses/LICENSE
django_gcp_cloudtasks-1.9.0.dist-info/METADATA
django_gcp_cloudtasks-1.9.0.dist-info/WHEEL
django_gcp_cloudtasks-1.9.0.dist-info/top_level.txt
django_gcp_cloudtasks-1.9.0.dist-info/RECORD
