Metadata-Version: 2.4
Name: django-gcp-cloudtasks
Version: 1.9.0
Summary: Google Cloud Tasks support for Django
Home-page: https://github.com/dm-nosov/django-cloudtasks
Author: Dmitry Nosov
Author-email: nosov.sibers@gmail.com
License: MIT
Classifier: Environment :: Web Environment
Classifier: Framework :: Django
Classifier: Intended Audience :: Developers
Classifier: Programming Language :: Python :: 3 :: Only
Classifier: Programming Language :: Python :: 3.9
Classifier: Programming Language :: Python :: 3.10
Classifier: Programming Language :: Python :: 3.11
Classifier: Programming Language :: Python :: 3.12
Classifier: Programming Language :: Python :: 3
Classifier: Framework :: Django :: 3.2
Classifier: Framework :: Django :: 4.2
Classifier: Framework :: Django :: 5.0
Requires-Python: >=3.9
License-File: LICENSE
Requires-Dist: django>=3.2
Requires-Dist: google-cloud-tasks>=2.13.0
Requires-Dist: requests>=2.28.2
Dynamic: author
Dynamic: author-email
Dynamic: classifier
Dynamic: description
Dynamic: description-content-type
Dynamic: home-page
Dynamic: license
Dynamic: license-file
Dynamic: requires-dist
Dynamic: requires-python
Dynamic: summary
